adafruit_rfm69.py
adafruit_circuitpython_rfm69-2.1.28.dist-info/licenses/LICENSE
adafruit_circuitpython_rfm69-2.1.28.dist-info/METADATA
adafruit_circuitpython_rfm69-2.1.28.dist-info/WHEEL
adafruit_circuitpython_rfm69-2.1.28.dist-info/top_level.txt
adafruit_circuitpython_rfm69-2.1.28.dist-info/RECORD
